LICENSE.md
MANIFEST.in
main.py
readme.md
setup.cfg
setup.py
tread/__init__.py
tread/controller.py
tread/default_config.yml
tread/models.py
tread.egg-info/PKG-INFO
tread.egg-info/SOURCES.txt
tread.egg-info/dependency_links.txt
tread.egg-info/entry_points.txt
tread.egg-info/not-zip-safe
tread.egg-info/requires.txt
tread.egg-info/top_level.txt