Metadata-Version: 1.1
Name: tread
Version: 0.9.3
Summary: A terminal feed reader.
Home-page: https://github.com/spurll/tread
Author: Gem Newman
Author-email: spurll@gmail.com
License: CC BY-SA 4.0
Download-URL: https://github.com/spurll/tread/tarball/0.9.3
Keywords: rss,feed,reader
Platform: UNKNOWN
Classifier: Intended Audience :: End Users/Desktop
Classifier: Environment :: Console :: Curses
Classifier: Development Status :: 4 - Beta
Classifier: Topic :: Internet
Classifier: Programming Language :: Python :: 3.5
